parler_rest/__init__.py
parler_rest/fields.py
parler_rest/serializers.py
parler_rest/utils.py
jst_parler_rest-1.0.1.dist-info/AUTHORS.md
jst_parler_rest-1.0.1.dist-info/LICENSE
jst_parler_rest-1.0.1.dist-info/METADATA
jst_parler_rest-1.0.1.dist-info/WHEEL
jst_parler_rest-1.0.1.dist-info/top_level.txt
jst_parler_rest-1.0.1.dist-info/RECORD
