Metadata-Version: 2.2
Name: jst-parler-rest
Version: 1.0.1
Summary: Multilingual support for django-rest-framework
Home-page: https://github.com/edoburu/django-parler-rest
Download-URL: https://github.com/edoburu/django-parler-rest/zipball/master
Author: Diederik van der Boor
Author-email: opensource@edoburu.nl
License: Apache 2.0
Classifier: Development Status :: 5 - Production/Stable
Classifier: Environment :: Web Environment
Classifier: Framework :: Django
Classifier: Intended Audience :: Developers
Classifier: License :: OSI Approved :: Apache Software License
Classifier: Operating System :: OS Independent
Classifier: Programming Language :: Python
Classifier: Programming Language :: Python :: 3.8
Classifier: Programming Language :: Python :: 3.9
Classifier: Programming Language :: Python :: 3.10
Classifier: Framework :: Django :: 2.2
Classifier: Framework :: Django :: 3.2
Classifier: Framework :: Django :: 4.0
License-File: LICENSE
License-File: AUTHORS.md
Requires-Dist: jst-parler>=1.0.0
Requires-Dist: djangorestframework>=3.5
Requires-Dist: django>=2.2
Dynamic: author
Dynamic: author-email
Dynamic: classifier
Dynamic: description
Dynamic: description-content-type
Dynamic: download-url
Dynamic: home-page
Dynamic: license
Dynamic: requires-dist
Dynamic: summary
